[
  {"firstName": "Alec", "lastName": "Budd", "country": "", "img": ""},
  {"firstName": "Alexander", "lastName": "Burdett", "country": "", "img": ""},
  {"firstName": "André", "lastName": "Sebastian", "country": "", "img": ""},
  {"firstName": "Ang Min", "lastName": "Sheng", "country": "", "img": ""},
  {"firstName": "Emmanuel", "lastName": "Iyere", "country": "", "img": ""},
  {"firstName": "Federico", "lastName": "Cassettai", "country": "", "img": ""},
  {"firstName": "Felix", "lastName": "Grosser", "country": "", "img": ""},
  {"firstName": "Franziska", "lastName": "Bath", "country": "", "img": ""},
  {"firstName": "Jamie", "lastName": "Egan", "country": "", "img": ""},
  {"firstName": "Jennifer", "lastName": "Roberts", "country": "", "img": ""},
  {"firstName": "Julia", "lastName": "Miller", "country": "", "img": ""},
  {"firstName": "Ksenia", "lastName": "Danniker", "country": "", "img": ""},
  {"firstName": "Laura", "lastName": "Puyol Rigol", "country": "", "img": ""},
  {"firstName": "Amelia", "lastName": "Chorng Ua", "country": "", "img": ""},
  {"firstName": "Malte", "lastName": "Felmy", "country": "", "img": ""},
  {"firstName": "Marvin", "lastName": "Artioli", "country": "", "img": ""},
  {"firstName": "Matt", "lastName": "Harrison", "country": "", "img": ""},
  {"firstName": "Moritz", "lastName": "Opitz", "country": "", "img": ""},
  {"firstName": "Na'aman", "lastName": "Hirschfeld", "country": "", "img": ""},
  {"firstName": "Pedro", "lastName": "Arantes", "country": "", "img": ""},
  {"firstName": "Petter", "lastName": "Åstedt", "country": "", "img": ""},
  {"firstName": "Ruby", "lastName": "Lai", "country": "", "img": ""},
  {"firstName": "Sinan", "lastName": "Taylan", "country": "", "img": ""},
  {"firstName": "Svenja", "lastName": "Weiler", "country": "", "img": ""}
]
